{"ExtraData":null,"Type":0,"Version":"1.0.0","Hashes":{"Files":[{"RelativePath":"BMD.File.Emulator.Interfaces.dll","Hash":752148817188957040},{"RelativePath":"BMD.File.Emulator.Interfaces.pdb","Hash":9588792412599473308},{"RelativePath":"CriFs.V2.Hook.Interfaces.dll","Hash":10976142352528684311},{"RelativePath":"CriFs.V2.Hook.Interfaces.pdb","Hash":14801078639914871858},{"RelativePath":"CriFsV2Lib.Definitions.dll","Hash":3658745127075729307},{"RelativePath":"ModConfig.json","Hash":8908174463931297250},{"RelativePath":"NaoSmiley.dll","Hash":10948853079380014124},{"RelativePath":"NaoSmiley.pdb","Hash":10683363307423875563},{"RelativePath":"p4gpc.signatureskillsplus.deps.json","Hash":9603849136254109633},{"RelativePath":"p4gpc.signatureskillsplus.dll","Hash":15307174959442458094},{"RelativePath":"p4gpc.signatureskillsplus.pdb","Hash":17977951082376280501},{"RelativePath":"PAK.Stream.Emulator.Interfaces.dll","Hash":11175603084066000557},{"RelativePath":"PAK.Stream.Emulator.Interfaces.pdb","Hash":10224754696656144661},{"RelativePath":"PAK.Stream.Emulator.Interfaces.xml","Hash":17129933017941485915},{"RelativePath":"Preview.png","Hash":1863136344086842605},{"RelativePath":"Reloaded.Hooks.Definitions.dll","Hash":3707225781942902320},{"RelativePath":"Reloaded.Hooks.ReloadedII.Interfaces.dll","Hash":4073583542395463031},{"RelativePath":"Yosuke Romance.deps.json","Hash":4479619461334428059},{"RelativePath":"Yosuke Romance.pdb","Hash":15926533431819944074},{"RelativePath":"Yosuke_Romance.dll","Hash":10441487962951322365},{"RelativePath":"Cadenza\\FEmulator\\BMD\\datSkillHelp.msg","Hash":15657836921389267877},{"RelativePath":"Door of Hades\\FEmulator\\BMD\\datSkillHelp.msg","Hash":4792679337660848331},{"RelativePath":"Myriad Truths\\FEmulator\\BMD\\datSkillHelp.msg","Hash":17601026192451079817},{"RelativePath":"Oratorio\\FEmulator\\BMD\\datSkillHelp.msg","Hash":15618587796138096563},{"RelativePath":"Shining Arrows\\FEmulator\\BMD\\datSkillHelp.msg","Hash":4118324077057344580},{"RelativePath":"Cadenza\\FEmulator\\PAK\\init_free.bin\\battle\\MSG.TBL","Hash":15234963723660543929},{"RelativePath":"Cadenza\\FEmulator\\PAK\\init_free.bin\\battle\\PERSONA.TBL","Hash":2749518400245367461},{"RelativePath":"Cadenza\\FEmulator\\PAK\\init_free.bin\\battle\\SKILL.TBL","Hash":6540665941399055610},{"RelativePath":"Cadenza\\P5REssentials\\CPK\\data.cpk\\skill\\1B1.pac","Hash":18208488448329439132},{"RelativePath":"Door of Hades\\FEmulator\\PAK\\init_free.bin\\battle\\MSG.TBL","Hash":13847833678461769609},{"RelativePath":"Door of Hades\\FEmulator\\PAK\\init_free.bin\\battle\\PERSONA.TBL","Hash":2273164768267070291},{"RelativePath":"Door of Hades\\FEmulator\\PAK\\init_free.bin\\battle\\SKILL.TBL","Hash":11571211689529045892},{"RelativePath":"Door of Hades\\P5REssentials\\CPK\\data.cpk\\skill\\1B2.pac","Hash":14724309003417310583},{"RelativePath":"Magatsu Mandala\\FEmulator\\PAK\\init_free.bin\\battle\\MSG.TBL","Hash":11686640629734662101},{"RelativePath":"Magatsu Mandala\\FEmulator\\PAK\\init_free.bin\\battle\\PERSONA.TBL","Hash":2896783486642331983},{"RelativePath":"Magatsu Mandala\\FEmulator\\PAK\\init_free.bin\\battle\\SKILL.TBL","Hash":8786060281731606670},{"RelativePath":"Magatsu Mandala\\P5REssentials\\CPK\\data.cpk\\skill\\1AC.pac","Hash":18160719270508201466},{"RelativePath":"Myriad Truths\\FEmulator\\PAK\\init_free.bin\\battle\\MSG.TBL","Hash":11592446953992295157},{"RelativePath":"Myriad Truths\\FEmulator\\PAK\\init_free.bin\\battle\\PERSONA.TBL","Hash":4770466307380965551},{"RelativePath":"Myriad Truths\\FEmulator\\PAK\\init_free.bin\\battle\\SKILL.TBL","Hash":14237401077043604367},{"RelativePath":"Myriad Truths\\P5REssentials\\CPK\\data.cpk\\skill\\1B3.pac","Hash":3802149182014944051},{"RelativePath":"Oratorio\\FEmulator\\PAK\\init_free.bin\\battle\\MSG.TBL","Hash":9466017133414537375},{"RelativePath":"Oratorio\\FEmulator\\PAK\\init_free.bin\\battle\\PERSONA.TBL","Hash":17301883572223691756},{"RelativePath":"Oratorio\\FEmulator\\PAK\\init_free.bin\\battle\\SKILL.TBL","Hash":14789625580133199391},{"RelativePath":"Oratorio\\P5REssentials\\CPK\\data.cpk\\skill\\1B0.pac","Hash":10076569971127874914},{"RelativePath":"Shining Arrows\\FEmulator\\PAK\\init_free.bin\\battle\\MSG.TBL","Hash":779927268430794608},{"RelativePath":"Shining Arrows\\FEmulator\\PAK\\init_free.bin\\battle\\PERSONA.TBL","Hash":7489352440181391771},{"RelativePath":"Shining Arrows\\FEmulator\\PAK\\init_free.bin\\battle\\SKILL.TBL","Hash":12072491836920080772},{"RelativePath":"Shining Arrows\\P5REssentials\\CPK\\data\\skill\\135.pac","Hash":7190512332438473835},{"RelativePath":"Cadenza\\FEmulator\\PAK\\init.bin\\init\\datMsg.pak\\datSkillHelp.bmd","Hash":17241709254077376921},{"RelativePath":"Door of Hades\\FEmulator\\PAK\\init.bin\\init\\datMsg.pak\\datSkillHelp.bmd","Hash":17241709254077376921},{"RelativePath":"Magatsu Mandala\\FEmulator\\PAK\\init.bin\\init\\datMsg.pak\\datSkillHelp.bmd","Hash":17241709254077376921},{"RelativePath":"Myriad Truths\\FEmulator\\PAK\\init.bin\\init\\datMsg.pak\\datSkillHelp.bmd","Hash":17241709254077376921},{"RelativePath":"Oratorio\\FEmulator\\PAK\\init.bin\\init\\datMsg.pak\\datSkillHelp.bmd","Hash":17241709254077376921},{"RelativePath":"Shining Arrows\\FEmulator\\PAK\\init.bin\\init\\datMsg.pak\\datSkillHelp.bmd","Hash":17241709254077376921}]},"IgnoreRegexes":[".*\\.json","p4gpc\\.signatureskillsplus\\.nuspec","p4gpc\\.signatureskillsplus\\.ReleaseMetadata\\.json"],"IncludeRegexes":["ModConfig\\.json","\\.deps\\.json","\\.runtimeconfig\\.json"],"DeltaData":null}